linien/VERSION
linien/__init__.py
linien/common.py
linien/config.py
linien/gui/__init__.py
linien/gui/app.py
linien/gui/config.py
linien/gui/dialogs.py
linien/gui/icon.ico
linien/gui/utils_gui.py
linien/gui/widgets.py
linien/gui/ui/__init__.py
linien/gui/ui/device_manager.py
linien/gui/ui/device_manager.ui
linien/gui/ui/general_panel.py
linien/gui/ui/general_panel.ui
linien/gui/ui/lock_status_panel.py
linien/gui/ui/locking_panel.py
linien/gui/ui/locking_panel.ui
linien/gui/ui/main_window.py
linien/gui/ui/main_window.ui
linien/gui/ui/modulation_sweep_panel.py
linien/gui/ui/modulation_sweep_panel.ui
linien/gui/ui/new_device_dialog.py
linien/gui/ui/new_device_dialog.ui
linien/gui/ui/optimization_panel.py
linien/gui/ui/optimization_panel.ui
linien/gui/ui/plot_widget.py
linien/gui/ui/psd_plot_widget.py
linien/gui/ui/psd_table_widget.py
linien/gui/ui/psd_window.py
linien/gui/ui/psd_window.ui
linien/gui/ui/right_panel.py
linien/gui/ui/spectroscopy_panel.py
linien/gui/ui/spectroscopy_panel.ui
linien/gui/ui/spin_box.py
linien/gui/ui/sweep_control.py
linien/gui/ui/version_checker.py
linien/gui/ui/view_panel.py
linien/gui/ui/view_panel.ui
linien-0.5.3.post2.dist-info/LICENSE
linien-0.5.3.post2.dist-info/METADATA
linien-0.5.3.post2.dist-info/WHEEL
linien-0.5.3.post2.dist-info/entry_points.txt
linien-0.5.3.post2.dist-info/top_level.txt
linien-0.5.3.post2.dist-info/RECORD
