Metadata-Version: 2.1
Name: linien
Version: 0.5.3.post2
Summary: Spectroscopy lock application using RedPitaya
Home-page: https://github.com/linien-org/linien
Author: Benjamin Wiegand
Author-email: highwaychile@posteo.de
Maintainer: Bastian Leykauf
Maintainer-email: leykauf@physik.hu-berlin.de
License: UNKNOWN
Platform: UNKNOWN
Classifier: Programming Language :: Python :: 3
Classifier: License :: OSI Approved :: GNU General Public License v3 (GPLv3)
Classifier: Operating System :: OS Independent
Requires-Dist: click (>=7.1.2)
Requires-Dist: numpy (>=1.19.1)
Requires-Dist: paramiko (>=2.10.1)
Requires-Dist: plumbum (>=1.6.9)
Requires-Dist: pyqtgraph (>=0.10.0)
Requires-Dist: PyQt5 (>=5.12.0)
Requires-Dist: rpyc (<5.0,>=4.0)
Requires-Dist: scipy (>=1.4.1)
Requires-Dist: superqt (>=0.2.3)
Requires-Dist: linien-python-client (==0.5.3-2)
